dianshangji/__init__.py
dianshangji/color.py
dianshangji/loader.py
dianshangji/palette.py
dianshangji/taobao.py
shuyouqi/__init__.py
shuyouqi/profiling.py
shuyouqi/util.py
shuyouqi-1.0.4.dist-info/METADATA
shuyouqi-1.0.4.dist-info/WHEEL
shuyouqi-1.0.4.dist-info/top_level.txt
shuyouqi-1.0.4.dist-info/RECORD
