Metadata-Version: 2.1
Name: shuyouqi
Version: 1.0.4
Summary: 电商记提供的自动化和探索性数据分析工具库
Home-page: https://shuyouqi.com
Author: shuyouqi.com
Author-email: dianshangji@qq.com
Classifier: Programming Language :: Python :: 3
Classifier: License :: OSI Approved :: MIT License
Classifier: Operating System :: OS Independent
Requires-Python: >=3.6
